power_grid_model/__init__.py
power_grid_model/data_types.py
power_grid_model/utils.py
power_grid_model/py.typed
power_grid_model/errors.py
power_grid_model/enum.py
power_grid_model/typing.py
power_grid_model/_core/options.py
power_grid_model/_core/power_grid_core.py
power_grid_model/_core/power_grid_model.py
power_grid_model/_core/__init__.py
power_grid_model/_core/buffer_handling.py
power_grid_model/_core/data_types.py
power_grid_model/_core/error_handling.py
power_grid_model/_core/power_grid_meta.py
power_grid_model/_core/dataset_definitions.py
power_grid_model/_core/utils.py
power_grid_model/_core/data_handling.py
power_grid_model/_core/errors.py
power_grid_model/_core/power_grid_dataset.py
power_grid_model/_core/index_integer.py
power_grid_model/_core/enum.py
power_grid_model/_core/typing.py
power_grid_model/_core/serialization.py
power_grid_model/_core/power_grid_model_c/__init__.py
power_grid_model/_core/power_grid_model_c/get_pgm_dll_path.py
power_grid_model/_core/power_grid_model_c/include/power_grid_model_c.h
power_grid_model/_core/power_grid_model_c/include/power_grid_model_cpp.hpp
power_grid_model/_core/power_grid_model_c/include/power_grid_model_cpp/dataset.hpp
power_grid_model/_core/power_grid_model_c/include/power_grid_model_cpp/meta_data.hpp
power_grid_model/_core/power_grid_model_c/include/power_grid_model_cpp/serialization.hpp
power_grid_model/_core/power_grid_model_c/include/power_grid_model_cpp/handle.hpp
power_grid_model/_core/power_grid_model_c/include/power_grid_model_cpp/model.hpp
power_grid_model/_core/power_grid_model_c/include/power_grid_model_cpp/options.hpp
power_grid_model/_core/power_grid_model_c/include/power_grid_model_cpp/buffer.hpp
power_grid_model/_core/power_grid_model_c/include/power_grid_model_cpp/utils.hpp
power_grid_model/_core/power_grid_model_c/include/power_grid_model_cpp/basics.hpp
power_grid_model/_core/power_grid_model_c/include/power_grid_model_c/serialization.h
power_grid_model-1.12.111.dist-info/RECORD
power_grid_model-1.12.111.dist-info/WHEEL
power_grid_model-1.12.111.dist-info/entry_points.txt
power_grid_model-1.12.111.dist-info/METADATA
power_grid_model-1.12.111.dist-info/licenses/LICENSE
