Metadata-Version: 2.4
Name: power-grid-model
Version: 1.12.111
Summary: Python/C++ library for distribution power system analysis
Author-Email: Contributors to the Power Grid Model project <powergridmodel@lfenergy.org>
License-Expression: MPL-2.0
Classifier: Programming Language :: Python :: 3
Classifier: Programming Language :: Python :: Implementation :: CPython
Classifier: Programming Language :: C++
Classifier: Development Status :: 5 - Production/Stable
Classifier: Intended Audience :: Developers
Classifier: Intended Audience :: Science/Research
Classifier: Operating System :: Microsoft :: Windows
Classifier: Operating System :: POSIX :: Linux
Classifier: Operating System :: MacOS
Classifier: Topic :: Scientific/Engineering :: Physics
Project-URL: Home-page, https://lfenergy.org/projects/power-grid-model/
Project-URL: GitHub, https://github.com/PowerGridModel/power-grid-model
Project-URL: Documentation, https://power-grid-model.readthedocs.io/en/stable/
Project-URL: Mailing-list, https://lists.lfenergy.org/g/powergridmodel
Project-URL: Discussion, https://github.com/orgs/PowerGridModel/discussions
Requires-Python: >=3.12
Requires-Dist: numpy>=2.0.0
